[
  {
    "就醫院所縣市別": "桃園市",
    "特約類別": "地區醫院",
    "醫事機構代碼": "1532040039",
    "醫事機構名稱": "天成醫院",
    "醫事機構簡稱": "天成醫院",
    "自付差額品項類別": "人工髖關節",
    "自付差額品項功能分類": "陶瓷髖臼杯內襯",
    "中文名稱": "\"西美\"西羅索高分子背架陶瓷髖臼植入物:陶瓷髖臼杯內襯",
    "英文名稱": "\"ZIMMER\"CERASUL POLY BACK OF CERAMIC LINER:CERAMIC LINER",
    "品項代碼": "FBHLCCERA1Z1",
    "許可證字號": "衛署醫器輸字第014436號",
    "健保給付點數": "4018.0",
    "特約院所收費": "30000",
    "分區業務組": "北區",
    "說明": "對應健保全額給付品項代碼"
  },
  {
    "就醫院所縣市別": "新北市",
    "特約類別": "地區醫院",
    "醫事機構代碼": "1231030015",
    "醫事機構名稱": "天主教耕莘醫療財團法人永和耕莘醫院",
    "醫事機構簡稱": "永和耕莘",
    "自付差額品項類別": "人工髖關節",
    "自付差額品項功能分類": "陶瓷髖臼杯內襯",
    "中文名稱": "\"西美\"西羅索高分子背架陶瓷髖臼植入物:陶瓷髖臼杯內襯",
    "英文名稱": "\"ZIMMER\"CERASUL POLY BACK OF CERAMIC LINER:CERAMIC LINER",
    "品項代碼": "FBHLCCERA1Z1",
    "許可證字號": "衛署醫器輸字第014436號",
    "健保給付點數": "4018.0",
    "特約院所收費": "29582",
    "分區業務組": "臺北",
    "說明": "對應健保全額給付品項代碼"
  },
  {
    "就醫院所縣市別": "桃園市",
    "特約類別": "區域醫院",
    "醫事機構代碼": "1532100049",
    "醫事機構名稱": "聯新國際醫院",
    "醫事機構簡稱": "聯新國際醫",
    "自付差額品項類別": "人工髖關節",
    "自付差額品項功能分類": "陶瓷髖臼杯內襯",
    "中文名稱": "\"西美\"西羅索高分子背架陶瓷髖臼植入物:陶瓷髖臼杯內襯",
    "英文名稱": "\"ZIMMER\"CERASUL POLY BACK OF CERAMIC LINER:CERAMIC LINER",
    "品項代碼": "FBHLCCERA1Z1",
    "許可證字號": "衛署醫器輸字第014436號",
    "健保給付點數": "4018.0",
    "特約院所收費": "32221",
    "分區業務組": "北區",
    "說明": "對應健保全額給付品項代碼"
  }
]