[
  {
    "就醫院所縣市別": "臺北市",
    "特約類別": "地區醫院",
    "醫事機構代碼": "1501010010",
    "醫事機構名稱": "博仁綜合醫院",
    "醫事機構簡稱": "博仁醫院",
    "自付差額品項類別": "冠狀動脈塗藥支架",
    "自付差額品項功能分類": "",
    "中文名稱": "\"波士頓科技\"博謨適艾勒門艾諾莉茉斯冠狀動脈塗藥支架系統",
    "英文名稱": "\"BOSTON SCIENTIFIC\"PROMUS ELEMENT EVEROLIMUS-ELUTING CORONARY STENT SYSTEM",
    "品項代碼": "CBP06ELUT5SB",
    "許可證字號": "衛署醫器輸字第021389號",
    "健保給付點數": "14099.0",
    "特約院所收費": "58420",
    "分區業務組": "臺北",
    "說明": "對應健保全額給付品項代碼"
  },
  {
    "就醫院所縣市別": "臺北市",
    "特約類別": "地區醫院",
    "醫事機構代碼": "1501010010",
    "醫事機構名稱": "博仁綜合醫院",
    "醫事機構簡稱": "博仁醫院",
    "自付差額品項類別": "冠狀動脈塗藥支架",
    "自付差額品項功能分類": "",
    "中文名稱": "\"亞培\"賽恩斯優艾諾莉茉斯冠狀動脈塗藥支架系統",
    "英文名稱": "\"ABBOTT\"XIENCE PRIME EVEROLIMUS ELUTING CORONARY STENT SYSTEM",
    "品項代碼": "CBP06ELUT3AB",
    "許可證字號": "衛署醫器輸字第021478號",
    "健保給付點數": "14099.0",
    "特約院所收費": "60687",
    "分區業務組": "臺北",
    "說明": "對應健保全額給付品項代碼"
  },
  {
    "就醫院所縣市別": "臺北市",
    "特約類別": "地區醫院",
    "醫事機構代碼": "1501010010",
    "醫事機構名稱": "博仁綜合醫院",
    "醫事機構簡稱": "博仁醫院",
    "自付差額品項類別": "冠狀動脈塗藥支架",
    "自付差額品項功能分類": "",
    "中文名稱": "\"柏盛\"拜美翠弗雷絲藥物釋放冠狀動脈支架系統",
    "英文名稱": "\"BIOSENSORS\"BIOMATRIX FLEX DRUG ELUTING CORONARY STENT SYSTEM",
    "品項代碼": "CBP06ELUT2BS",
    "許可證字號": "衛署醫器輸字第023108號",
    "健保給付點數": "14099.0",
    "特約院所收費": "57817",
    "分區業務組": "臺北",
    "說明": "對應健保全額給付品項代碼"
  },
  {
    "就醫院所縣市別": "臺北市",
    "特約類別": "地區醫院",
    "醫事機構代碼": "1501010010",
    "醫事機構名稱": "博仁綜合醫院",
    "醫事機構簡稱": "博仁醫院",
    "自付差額品項類別": "人工心律調節器",
    "自付差額品項功能分類": "",
    "中文名稱": "\"美敦力\"艾維莎核磁共振植入式心臟節律器",
    "英文名稱": "\"MEDTRONIC\"ADVISA DR MRI SURESCAN IMPLANTABLE PACEMAKER",
    "品項代碼": "FHP02A3DR1M4",
    "許可證字號": "衛署醫器輸字第023118號",
    "健保給付點數": "93833.0",
    "特約院所收費": "57000",
    "分區業務組": "臺北",
    "說明": "對應健保全額給付品項代碼"
  },
  {
    "就醫院所縣市別": "臺北市",
    "特約類別": "地區醫院",
    "醫事機構代碼": "1501010010",
    "醫事機構名稱": "博仁綜合醫院",
    "醫事機構簡稱": "博仁醫院",
    "自付差額品項類別": "冠狀動脈塗藥支架",
    "自付差額品項功能分類": "",
    "中文名稱": "\"美敦力\"律動英泰爾釋放型冠狀動脈支架系統",
    "英文名稱": "\"MEDTRONIC\"RESOLUTE INTEGRITY ZOTAROLIMUS-ELUTING CORONARY STENT SYSTEM",
    "品項代碼": "CBP06ELUT5M4",
    "許可證字號": "衛署醫器輸字第024020號",
    "健保給付點數": "14099.0",
    "特約院所收費": "59313",
    "分區業務組": "臺北",
    "說明": "對應健保全額給付品項代碼"
  },
  {
    "就醫院所縣市別": "臺北市",
    "特約類別": "地區醫院",
    "醫事機構代碼": "1501010010",
    "醫事機構名稱": "博仁綜合醫院",
    "醫事機構簡稱": "博仁醫院",
    "自付差額品項類別": "冠狀動脈塗藥支架",
    "自付差額品項功能分類": "",
    "中文名稱": "\"泰爾茂\"阿提瑪斯特丹誠冠狀動脈塗藥支架系統",
    "英文名稱": "\"TERUMO\" Ultimaster Tansei Sirolimus Eluting Coronary Stent System",
    "品項代碼": "CBP06ELUT3TM",
    "許可證字號": "衛部醫器輸字第031249號",
    "健保給付點數": "14099.0",
    "特約院所收費": "61851",
    "分區業務組": "臺北",
    "說明": "對應健保全額給付品項代碼"
  }
]